ThreadedCommand-0.2.data/scripts/tcommand
threadedcommand/__init__.py
ThreadedCommand-0.2.dist-info/LICENSE
ThreadedCommand-0.2.dist-info/METADATA
ThreadedCommand-0.2.dist-info/WHEEL
ThreadedCommand-0.2.dist-info/top_level.txt
ThreadedCommand-0.2.dist-info/RECORD
