Metadata-Version: 2.1
Name: ThreadedCommand
Version: 0.2
Summary: Runs a console command in multiple threads
Home-page: https://github.com/mibexx/threaded_command
Author: Mike Bertram
Author-email: contact@mibexx.de
License: UNKNOWN
Platform: UNKNOWN
Classifier: Programming Language :: Python :: 3
Classifier: License :: OSI Approved :: MIT License
Classifier: Operating System :: OS Independent
